bulk_docker_inspection/__init__.py
bulk_docker_inspection/importlib_runner.py
bulk_docker_inspection/main.py
bulk_docker_inspection/runner.py
bulk_docker_inspection/samples/__init__.py
bulk_docker_inspection/samples/python_info.py
bulk_docker_inspection/samples/system_info.py
bulk_docker_inspection-0.0.1.dist-info/licenses/LICENSE
bulk_docker_inspection-0.0.1.dist-info/METADATA
bulk_docker_inspection-0.0.1.dist-info/WHEEL
bulk_docker_inspection-0.0.1.dist-info/top_level.txt
bulk_docker_inspection-0.0.1.dist-info/RECORD
