Metadata-Version: 2.4
Name: bulk-docker-inspection
Version: 0.0.1
Summary: Whats in there!
Author: Carter Fendley
License: MIT License
Project-URL: Homepage, https://github.com/CarterFendley/bulk-docker-inspection
License-File: LICENSE
Requires-Dist: cloudpickle
Provides-Extra: dev
Requires-Dist: tox; extra == "dev"
Requires-Dist: pytest; extra == "dev"
Requires-Dist: pytest-cov; extra == "dev"
Requires-Dist: pytest-unordered; extra == "dev"
Dynamic: license-file
